CONTRIBUTING.md
LICENSE
MANIFEST.in
Makefile
README.md
pyproject.toml
setup.py
aws_ket.egg-info/PKG-INFO
aws_ket.egg-info/SOURCES.txt
aws_ket.egg-info/dependency_links.txt
aws_ket.egg-info/top_level.txt
awsket/app.py
awsket/ket.py