Metadata-Version: 2.1
Name: aws-ket
Version: 0.1.6
Summary: Utility tool to encrypt data using AWS KMS and store it in preferred backend.
Home-page: https://github.com/sayefiqb/aws-ket
Author: Sayef Iqbal
Author-email: s2400@columbia.edu
Maintainer: Sayef Iqbal
License: UNKNOWN
Platform: UNKNOWN
License-File: LICENSE
